passport/socialplay.py
django_social_passport-0.0.2.dist-info/LICENSE
django_social_passport-0.0.2.dist-info/METADATA
django_social_passport-0.0.2.dist-info/WHEEL
django_social_passport-0.0.2.dist-info/top_level.txt
django_social_passport-0.0.2.dist-info/RECORD
