Metadata-Version: 2.1
Name: django-social-passport
Version: 0.0.2
Summary: A Python library for seamless social authentication integration with Django.
Author-email: Diwash Lamichhane <diwash.happycoder@gmail.com>
Project-URL: Homepage, https://github.com/lamdiv/django-social-passport
Classifier: Programming Language :: Python :: 3
Classifier: Programming Language :: Python :: 3.7
Classifier: Programming Language :: Python :: 3.8
Classifier: Programming Language :: Python :: 3.9
Classifier: Programming Language :: Python :: 3.10
Classifier: License :: OSI Approved :: MIT License
Classifier: Operating System :: OS Independent
Requires-Python: >=3.7
License-File: LICENSE
